bignole/__init__.py
bignole/utils.py
bignole/core/__init__.py
bignole/core/exceptions.py
bignole/core/lexer.py
bignole/core/parser.py
bignole/core/processor.py
bignole/endpoints/__init__.py
bignole/endpoints/check.py
bignole/endpoints/cli.py
bignole/endpoints/common.py
bignole/endpoints/daemon.py
bignole/endpoints/templates.py
bignole/templater/__init__.py
bignole/templater/dummy.py
bignole/templater/jinja.py
bignole/templater/mako.py
bignole-0.1.2.dist-info/METADATA
bignole-0.1.2.dist-info/WHEEL
bignole-0.1.2.dist-info/entry_points.txt
bignole-0.1.2.dist-info/licenses/LICENSE
bignole-0.1.2.dist-info/RECORD
