Metadata-Version: 2.4
Name: bignole
Version: 0.1.2
Summary: Small utility/daemon which is intended to help human to maintain their SSH configs
Project-URL: repository, https://framagit.org/fiat-tux/bignole
Project-URL: Tracker, https://framagit.org/fiat-tux/bignole/-/issues
Author-email: Sergey Arkhipov <serge@aerialsounds.org>, Luc Didry <luc.bignole@didry.org>
License-Expression: MIT
License-File: LICENSE
Keywords: SSH,concierge
Classifier: Intended Audience :: Information Technology
Classifier: Intended Audience :: System Administrators
Classifier: Operating System :: POSIX :: Linux
Classifier: Programming Language :: Python
Classifier: Programming Language :: Python :: 3
Classifier: Programming Language :: Python :: 3.11
Requires-Python: >=3.11
Requires-Dist: inotify-simple
Provides-Extra: dev
Requires-Dist: hatch<2,>=1.14.1; extra == 'dev'
Requires-Dist: mypy<2,>=1.16.1; extra == 'dev'
Requires-Dist: pylint<4,>=3.3.7; extra == 'dev'
Requires-Dist: ruff<1,>=0.12.2; extra == 'dev'
Requires-Dist: types-pyyaml; extra == 'dev'
Provides-Extra: jinja
Requires-Dist: jinja2<4,>=3.1.6; extra == 'jinja'
Provides-Extra: mako
Requires-Dist: mako<2,>=1.3.10; extra == 'mako'
Provides-Extra: test
Requires-Dist: pytest-cov<7,>=6.2.1; extra == 'test'
Requires-Dist: pytest<9,>=8.4.1; extra == 'test'
